pygments_nushell/__init__.py
pygments_nushell/py.typed
pygments_nushell-0.4.0.dist-info/METADATA
pygments_nushell-0.4.0.dist-info/WHEEL
pygments_nushell-0.4.0.dist-info/entry_points.txt
pygments_nushell-0.4.0.dist-info/licenses/LICENSE
pygments_nushell-0.4.0.dist-info/RECORD
