Metadata-Version: 2.4
Name: pygments-nushell
Version: 0.4.0
Summary: Nushell lexer for Pygments
Author-email: James Dugan <jdugan6240@vivaldi.net>
License-Expression: 0BSD
License-File: LICENSE
Requires-Python: >=3.10
Requires-Dist: pygments>=2.19.2
